[{"mentions": ["Knack"], "hashtags": null, "urls": ["http://t.co/lvpTKOD0pH"], "emojis": null, "text": "Zo te zien heeft Johan Vande Lanotte de heisa met zijn windmolens nog niet goed verteerd... via @Knack", "created_at": "2014-12-05T09:31:00Z", "author_id": 83319460, "public_metrics": {"retweet_count": 0, "reply_count": 0, "like_count": 0, "quote_count": 0, "impression_count": 0}, "id": 540800495573819393, "sentiment": "NEGATIVE", "keyword": " Johan Vande Lanotte", "gov_type": "flemish"}, {"mentions": ["PatDS57", "Kherbache"], "hashtags": null, "urls": null, "emojis": null, "text": "@PatDS57 @Kherbache Nee, nee ik bedoel Johan Vande Lanotte, die kerel vh lege Zilverfonds en v 97miljoen euro verbrast geld in Electrawinds.", "created_at": "2014-11-24T21:49:49Z", "author_id": 2730000799, "public_metrics": {"retweet_count": 0, "reply_count": 2, "like_count": 0, "quote_count": 0, "impression_count": 0}, "id": 537000160329728000, "sentiment": "NEGATIVE", "keyword": " Johan Vande Lanotte", "gov_type": "flemish"}, {"mentions": null, "hashtags": ["ToekomstBelgischFederalisme"], "urls": ["http://t.co/nzVXJVWChG"], "emojis": null, "text": "Prof. Johan Vande Lanotte (UGent) en Stefan Sottiaux (KUL) discussiren over #ToekomstBelgischFederalisme", "created_at": "2014-11-12T13:39:37Z", "author_id": 2709673789, "public_metrics": {"retweet_count": 0, "reply_count": 0, "like_count": 2, "quote_count": 0, "impression_count": 0}, "id": 532528141370425344, "sentiment": "NEUTRAL", "keyword": " Johan Vande Lanotte", "gov_type": "flemish"}, {"mentions": ["destandaard"], "hashtags": ["Vande_Lanotte"], "urls": null, "emojis": null, "text": "@destandaard Schande! Johan #Vande_Lanotte zou dat uit zijn eigen zak moeten betalen of terechtstaan voor verkwisting van overheidsgeld!", "created_at": "2014-10-06T12:56:39Z", "author_id": 231962160, "public_metrics": {"retweet_count": 0, "reply_count": 0, "like_count": 0, "quote_count": 0, "impression_count": 0}, "id": 519108978098581504, "sentiment": "NEGATIVE", "keyword": " Johan Vande Lanotte", "gov_type": "flemish"}, {"mentions": null, "hashtags": null, "urls": ["http://t.co/XhraLNZcEm"], "emojis": null, "text": "Johan Vande Lanotte: 'N-VA moet premier leveren' - Belgi - Knack.be - ...", "created_at": "2014-09-18T09:26:31Z", "author_id": 1247165024, "public_metrics": {"retweet_count": 0, "reply_count": 0, "like_count": 0, "quote_count": 0, "impression_count": 0}, "id": 512533113592119296, "sentiment": "NEUTRAL", "keyword": " Johan Vande Lanotte", "gov_type": "flemish"}, {"mentions": ["radio1be"], "hashtags": ["deochtend"], "urls": null, "emojis": null, "text": "Dezelfde die pensioenprobleem minimaliseerde? \"@radio1be: Johan Vande Lanotte (SP.a) minimaliseert dreigende blackout. #deochtend\"", "created_at": "2014-08-20T05:44:00Z", "author_id": 313195811, "public_metrics": {"retweet_count": 8, "reply_count": 2, "like_count": 3, "quote_count": 0, "impression_count": 0}, "id": 501967867722891265, "sentiment": "NEUTRAL", "keyword": " Johan Vande Lanotte", "gov_type": "flemish"}, {"mentions": ["lutdebisschop"], "hashtags": ["Vande_Lanotte", "terzaketv"], "urls": null, "emojis": null, "text": "@lutdebisschop De winkels MOETEN je informeren; dat zegt toch Johan #Vande_Lanotte minister en prof grondwettelijk recht! #terzaketv", "created_at": "2014-07-29T18:36:05Z", "author_id": 231962160, "public_metrics": {"retweet_count": 0, "reply_count": 0, "like_count": 0, "quote_count": 0, "impression_count": 0}, "id": 494189634264776704, "sentiment": "NEGATIVE", "keyword": " Johan Vande Lanotte", "gov_type": "flemish"}, {"mentions": ["laurestuyck", "RuttenGwendolyn", "BenWeyts"], "hashtags": null, "urls": null, "emojis": null, "text": "@laurestuyck @RuttenGwendolyn @BenWeyts ze had dat beter gevraagd aan Johan Vande Lanotte met wie ze al decennia in regering zitten", "created_at": "2014-05-20T19:43:06Z", "author_id": 322706289, "public_metrics": {"retweet_count": 0, "reply_count": 0, "like_count": 0, "quote_count": 0, "impression_count": 0}, "id": 468839350026133504, "sentiment": "NEUTRAL", "keyword": " Johan Vande Lanotte", "gov_type": "flemish"}, {"mentions": null, "hashtags": null, "urls": ["http://t.co/m1Ra9746W8"], "emojis": null, "text": "Johan Vande Lanotte wil gratis voor de VN gaan werken - Belgi - Knack.be - Dat gratis van de sossen kennen wij", "created_at": "2014-05-03T11:07:45Z", "author_id": 1247165024, "public_metrics": {"retweet_count": 2, "reply_count": 1, "like_count": 2, "quote_count": 0, "impression_count": 0}, "id": 462549062924132352, "sentiment": "NEUTRAL", "keyword": " Johan Vande Lanotte", "gov_type": "flemish"}, {"mentions": null, "hashtags": null, "urls": ["http://t.co/gP0X15eI44"], "emojis": null, "text": "Johan Vande Lanotte: 'Wij willen niet terug naar de jaren 80' - Het Nieuwsblad Mobile - Naar de middeleeuwen ?", "created_at": "2014-05-01T19:08:43Z", "author_id": 1247165024, "public_metrics": {"retweet_count": 0, "reply_count": 1, "like_count": 0, "quote_count": 0, "impression_count": 0}, "id": 461945327378243586, "sentiment": "NEUTRAL", "keyword": " Johan Vande Lanotte", "gov_type": "flemish"}, {"mentions": null, "hashtags": ["DeStemVanVlaanderen"], "urls": ["http://t.co/wT2J6sIJlD"], "emojis": null, "text": "Ik heb meegedaan aan #DeStemVanVlaanderen en lijk het meest op Johan Vande Lanotte. Doe ook mee!", "created_at": "2014-04-18T06:06:00Z", "author_id": 38069243, "public_metrics": {"retweet_count": 0, "reply_count": 0, "like_count": 0, "quote_count": 0, "impression_count": 0}, "id": 457037310299996160, "sentiment": "POSITIVE", "keyword": " Johan Vande Lanotte", "gov_type": "flemish"}, {"mentions": null, "hashtags": ["JVDL", "dwarsligger"], "urls": ["https://t.co/GsSYAzpN6a"], "emojis": null, "text": "En Johan Vande Lanotte zelf? Die schrijft niet, maar schrapt. En hij legt ook uit waarom: #JVDL #dwarsligger", "created_at": "2014-03-18T20:20:42Z", "author_id": 30331123, "public_metrics": {"retweet_count": 1, "reply_count": 1, "like_count": 1, "quote_count": 0, "impression_count": 0}, "id": 446018376838942720, "sentiment": "NEGATIVE", "keyword": " Johan Vande Lanotte", "gov_type": "flemish"}, {"mentions": ["petertossyn"], "hashtags": null, "urls": ["http://t.co/Y4laarCZhC"], "emojis": null, "text": "@petertossyn Informeer eens bij \"uw vriend\" Johan.", "created_at": "2014-03-17T13:44:27Z", "author_id": 30331123, "public_metrics": {"retweet_count": 0, "reply_count": 1, "like_count": 0, "quote_count": 0, "impression_count": 0}, "id": 445556270838591488, "sentiment": "NEUTRAL", "keyword": " Johan Vande Lanotte", "gov_type": "flemish"}, {"mentions": null, "hashtags": null, "urls": ["http://t.co/dMJ7nRZtZ6"], "emojis": null, "text": "Johan Vande Lanotte: 'Descheemaecker pleegde chantage' - Belgi - Knack.be -", "created_at": "2014-03-12T10:55:19Z", "author_id": 1247165024, "public_metrics": {"retweet_count": 0, "reply_count": 0, "like_count": 0, "quote_count": 0, "impression_count": 0}, "id": 443701768615366656, "sentiment": "NEUTRAL", "keyword": " Johan Vande Lanotte", "gov_type": "flemish"}, {"mentions": null, "hashtags": ["DeTijd"], "urls": null, "emojis": null, "text": "Johan Vande Lanotte wil een label voor beleggingsproducten . Geldt dat ook voor Electrawinds, Groenkracht enz. ?#DeTijd", "created_at": "2014-02-27T08:29:30Z", "author_id": 166555933, "public_metrics": {"retweet_count": 6, "reply_count": 2, "like_count": 9, "quote_count": 0, "impression_count": 0}, "id": 438954026831724544, "sentiment": "NEUTRAL", "keyword": " Johan Vande Lanotte", "gov_type": "flemish"}, {"mentions": null, "hashtags": ["jogan", "verzekering"], "urls": ["http://t.co/5sTQtVy6Wx"], "emojis": null, "text": "Jaarvergadering Assuralia. Voorzitterswissel en speech Johan vande Lanotte #jogan #verzekering", "created_at": "2014-02-26T16:23:36Z", "author_id": 313195811, "public_metrics": {"retweet_count": 0, "reply_count": 2, "like_count": 0, "quote_count": 0, "impression_count": 0}, "id": 438710951916077056, "sentiment": "NEUTRAL", "keyword": " Johan Vande Lanotte", "gov_type": "flemish"}]