[{"mentions": ["jgalant74"], "hashtags": ["EU", "terzaketv", "deafspraak"], "urls": ["https://t.co/j4kzoSBUfA"], "emojis": null, "text": "Jacqueline Galant cest moi @jgalant74 als Tante Sidonia #EU Marianne Thyssen dit had geweten het kot was te klein #terzaketv #deafspraak", "created_at": "2017-01-13T11:04:21Z", "author_id": 2830094363, "public_metrics": {"retweet_count": 0, "reply_count": 0, "like_count": 0, "quote_count": 0, "impression_count": 0}, "id": 819862646333833216, "sentiment": "NEGATIVE", "keyword": "Jacqueline Galant", "gov_type": "flemish"}]