[{"mentions": null, "hashtags": ["FordGenk", "AlexanderDeCroo", "brugpensioen"], "urls": ["http://t.co/oJUWqYwY"], "emojis": null, "text": "'Alexander De Croo is een harteloze tuinkabouter' #FordGenk #AlexanderDeCroo #brugpensioen", "created_at": "2012-10-26T13:10:03Z", "author_id": 284177605, "public_metrics": {"retweet_count": 0, "reply_count": 0, "like_count": 0, "quote_count": 0, "impression_count": 0}, "id": 261816965767782401, "sentiment": "NEUTRAL", "keyword": "Alexander De Croo", "gov_type": "flemish"}, {"mentions": null, "hashtags": ["vk2012"], "urls": ["http://t.co/lep21F9I"], "emojis": null, "text": "Alexander De Croo wordt vicepremier #vk2012", "created_at": "2012-10-18T12:00:03Z", "author_id": 167309264, "public_metrics": {"retweet_count": 0, "reply_count": 0, "like_count": 0, "quote_count": 0, "impression_count": 0}, "id": 258900244920684544, "sentiment": "NEUTRAL", "keyword": "Alexander De Croo", "gov_type": "flemish"}, {"mentions": null, "hashtags": ["hetnieuwsvtm", "video"], "urls": ["http://t.co/Um8KIvyB"], "emojis": null, "text": "Alexander De Croo wordt minister van Pensioenen #hetnieuwsvtm #video", "created_at": "2012-10-18T05:35:17Z", "author_id": 167309264, "public_metrics": {"retweet_count": 0, "reply_count": 0, "like_count": 0, "quote_count": 0, "impression_count": 0}, "id": 258803417311494144, "sentiment": "NEUTRAL", "keyword": "Alexander De Croo", "gov_type": "flemish"}, {"mentions": null, "hashtags": ["hetnieuwsvtm", "video"], "urls": ["http://t.co/5axhaXvD"], "emojis": null, "text": "Alexander De Croo wil vader opvolgen als burgemeester #hetnieuwsvtm #video", "created_at": "2012-10-03T18:43:18Z", "author_id": 167309264, "public_metrics": {"retweet_count": 1, "reply_count": 1, "like_count": 0, "quote_count": 0, "impression_count": 0}, "id": 253565910978269186, "sentiment": "NEUTRAL", "keyword": "Alexander De Croo", "gov_type": "flemish"}, {"mentions": ["destandaard"], "hashtags": ["fan"], "urls": ["http://t.co/zL8I83ki"], "emojis": null, "text": "Yesss daar is ie weer! #fan \"@destandaard: De Gucht twijfelt aan Alexander De Croo \"", "created_at": "2012-09-13T07:42:51Z", "author_id": 223967918, "public_metrics": {"retweet_count": 0, "reply_count": 0, "like_count": 0, "quote_count": 0, "impression_count": 0}, "id": 246151942592679936, "sentiment": "POSITIVE", "keyword": "Alexander De Croo", "gov_type": "flemish"}, {"mentions": ["Nieuwsblad_be"], "hashtags": null, "urls": ["http://t.co/N1tOLi3X"], "emojis": null, "text": "zo van stok en hoenderhok en zo ... @Nieuwsblad_be: De Gucht twijfelt aan Alexander De Croo", "created_at": "2012-09-13T05:09:12Z", "author_id": 118165013, "public_metrics": {"retweet_count": 0, "reply_count": 0, "like_count": 0, "quote_count": 0, "impression_count": 0}, "id": 246113276545622016, "sentiment": "NEUTRAL", "keyword": "Alexander De Croo", "gov_type": "flemish"}, {"mentions": null, "hashtags": ["jupilerblue", "maes"], "urls": ["http://t.co/sy7FSfKb"], "emojis": null, "text": "Die blikjes trekken even fel op elkaar als Alexander De Croo en Smurfin. Ze zijn ook allebei blauw. #jupilerblue #maes", "created_at": "2012-07-06T16:53:18Z", "author_id": 105216587, "public_metrics": {"retweet_count": 0, "reply_count": 0, "like_count": 0, "quote_count": 0, "impression_count": 0}, "id": 221285706541187072, "sentiment": "POSITIVE", "keyword": "Alexander De Croo", "gov_type": "flemish"}, {"mentions": null, "hashtags": ["DeCroo", "Ochtend", "Radio1", "NVA"], "urls": ["http://t.co/wjaTQ3dN"], "emojis": null, "text": "Alexander #DeCroo bevestigde vandaag ongewild in De #Ochtend #Radio1 de correcte inschatting van de N-VA. #NVA", "created_at": "2012-06-13T15:13:06Z", "author_id": 607230104, "public_metrics": {"retweet_count": 0, "reply_count": 0, "like_count": 0, "quote_count": 0, "impression_count": 0}, "id": 212925569703215106, "sentiment": "NEUTRAL", "keyword": "Alexander De Croo", "gov_type": "flemish"}, {"mentions": null, "hashtags": ["BDW", "zerotolerance", "lachgas"], "urls": ["http://t.co/Gccv4S7B", "http://t.co/1Tdm3A56"], "emojis": null, "text": "Alexander De Croo eist net als #BDW #zerotolerance via GAS kwaal voorgesteld als remedie #lachgas", "created_at": "2012-04-14T09:42:58Z", "author_id": 482802074, "public_metrics": {"retweet_count": 0, "reply_count": 0, "like_count": 0, "quote_count": 0, "impression_count": 0}, "id": 191099217169743874, "sentiment": "NEUTRAL", "keyword": "Alexander De Croo", "gov_type": "flemish"}]